naviance/Naviance.py
naviance/__init__.py
naviance_client-0.0.2.dist-info/DESCRIPTION.rst
naviance_client-0.0.2.dist-info/LICENSE.txt
naviance_client-0.0.2.dist-info/METADATA
naviance_client-0.0.2.dist-info/RECORD
naviance_client-0.0.2.dist-info/WHEEL
naviance_client-0.0.2.dist-info/metadata.json
naviance_client-0.0.2.dist-info/top_level.txt
